{
    "game_id1": {
        "teams": [
            {
                "name": "",
                "score": "s1",
                "mvp": {
                    "name": "n1",
                    "pts": "n1"
                },
                "logo": ""
            },
            {
                "name": "",
                "score": "s1",
                "mvp": {
                    "name": "n1",
                    "pts": "n1"
                },
                "logo": ""
            }
        ],
        "place": "bala"
    },
    "game_id2": {
        "teams": [
            {
                "name": "",
                "score": "s1",
                "mvp": {
                    "name": "n1",
                    "pts": "n1"
                },
                "logo": ""
            },
            {
                "name": "",
                "score": "s1",
                "mvp": {
                    "name": "n1",
                    "pts": "n1"
                },
                "logo": ""
            }
        ]
    }